setup.py
clic_inference_extensions/__init__.py
clic_inference_extensions/bind.cpp
clic_inference_extensions/common.h
clic_inference_extensions/def.h
clic_inference_extensions/impl.cpp
clic_inference_extensions/kernel.cu
clic_inference_extensions.egg-info/PKG-INFO
clic_inference_extensions.egg-info/SOURCES.txt
clic_inference_extensions.egg-info/dependency_links.txt
clic_inference_extensions.egg-info/requires.txt
clic_inference_extensions.egg-info/top_level.txt