Metadata-Version: 2.4
Name: clic_inference_extensions
Version: 0.1.0.post1
Summary: PyTorch CUDA extension for fast inference of DCVC-RT
Author: Zhaoyang Jia, Bin Li, Jiahao Li, Wenxuan Xie, Linfeng Qi, Houqiang Li, Yan Lu
Author-email: jzy_ustc@mail.ustc.edu.cn, qlf324@mail.ustc.edu.cn, libin@microsoft.com, li.jiahao@microsoft.com, wenxie@microsoft.com, lihq@ustc.edu.cn, yanlu@microsoft.com
Maintainer: Wei Jiang
Maintainer-email: jiangwei@stu.pku.edu.cn
License: MIT
Classifier: Programming Language :: Python :: 3
Classifier: License :: OSI Approved :: MIT License
Requires-Python: >=3.11
Requires-Dist: torch>=1.10
Dynamic: author
Dynamic: author-email
Dynamic: classifier
Dynamic: description-content-type
Dynamic: license
Dynamic: maintainer
Dynamic: maintainer-email
Dynamic: requires-dist
Dynamic: requires-python
Dynamic: summary
